python_management_blueprint/__init__.py
python_management_blueprint/management/__init__.py
python_management_blueprint/management/app_info.py
python_management_blueprint/management/health_check.py
python_management_blueprint/management/management_resource.py
samples/__init__.py
samples/api.py
samples/run.py
sanic_management_blueprint/__init__.py
sanic_management_blueprint/management/__init__.py
sanic_management_blueprint/management/app_info.py
sanic_management_blueprint/management/health_check.py
sanic_management_blueprint/management/health_status.py
sanic_management_blueprint/management/management_resource.py
sanic_management_blueprint-0.1.0.dist-info/DESCRIPTION.rst
sanic_management_blueprint-0.1.0.dist-info/METADATA
sanic_management_blueprint-0.1.0.dist-info/RECORD
sanic_management_blueprint-0.1.0.dist-info/WHEEL
sanic_management_blueprint-0.1.0.dist-info/metadata.json
sanic_management_blueprint-0.1.0.dist-info/top_level.txt
stoneco_sanic_management_blueprint/__init__.py
stoneco_sanic_management_blueprint/management/__init__.py
stoneco_sanic_management_blueprint/management/app_info.py
stoneco_sanic_management_blueprint/management/health_check.py
stoneco_sanic_management_blueprint/management/management_resource.py
tests/unit/__init__.py
tests/unit/management/__init__.py
tests/unit/management/test_app_info.py
tests/unit/management/test_health_check.py
