Metadata-Version: 2.0
Name: sanic-management-blueprint
Version: 0.1.0
Summary: Sanic Management Blueprint
Home-page: https://github.com/stone-payments/sanic-management-blueprint
Author: UNKNOWN
Author-email: UNKNOWN
License: UNKNOWN
Platform: UNKNOWN
Requires-Dist: aiofiles
Requires-Dist: httptools
Requires-Dist: sanic
Requires-Dist: ujson
Requires-Dist: uvloop
Requires-Dist: websockets
Requires-Dist: async-timeout
Requires-Dist: aiohttp
